qcalc.py
qcalc-7.3.3.dist-info/METADATA
qcalc-7.3.3.dist-info/WHEEL
qcalc-7.3.3.dist-info/entry_points.txt
qcalc-7.3.3.dist-info/top_level.txt
qcalc-7.3.3.dist-info/RECORD
