Metadata-Version: 2.1
Name: qcalc
Version: 7.3.3
Summary: qcalc programmer's calculator
Home-page: https://www.state-machine.com/qtools/qcalc.html
Author: Quantum Leaps
Author-email: info@state-machine.com
License: GPL/commercial
Platform: any
Classifier: Development Status :: 5 - Production/Stable
Classifier: Intended Audience :: Developers
Classifier: Topic :: Software Development :: Embedded Systems
Classifier: License :: OSI Approved :: GNU General Public License v3 or later (GPLv3+)
Classifier: License :: Other/Proprietary License
Classifier: Operating System :: Microsoft :: Windows
Classifier: Operating System :: POSIX :: Linux
Classifier: Operating System :: MacOS :: MacOS X
Classifier: Programming Language :: Python
Classifier: Programming Language :: Python :: 3
